<MotorVehicleLicenceResponse xmlns="http://egov.bg/RegiX/BABH/BABHZhS/MotorVehicleLicenceResponse"><MotorVehicleData><MotorVehicleType>value</MotorVehicleType><RegistrationNumber>value</RegistrationNumber><Area>value</Area><Status>value</Status><StatusDate>0001-01-01T00:00:00</StatusDate><AdditionalInfo>nqma</AdditionalInfo></MotorVehicleData><LicencesData><LicenceType>MPS</LicenceType><LicenceNumber>7845</LicenceNumber><DateFrom>0001-01-01T00:00:00</DateFrom><DateTo>0001-01-01T00:00:00</DateTo><RevokeReason>nqma</RevokeReason></LicencesData><UsedAnimalTypes><AnimalKind>kuche</AnimalKind><Count>0</Count></UsedAnimalTypes><ReltionshipsData><RelationshipType>asd</RelationshipType><Name>value</Name><Identificator>9021112358</Identificator><DateFrom>0001-01-01T00:00:00</DateFrom><DateTo>0001-01-01T00:00:00</DateTo></ReltionshipsData></MotorVehicleLicenceResponse>
